whatsapp_api_webhook_server_python/__init__.py
whatsapp_api_webhook_server_python/webhooks.py
whatsapp_api_webhook_server_python/webhooksHandler.py
whatsapp_api_webhook_server_python-0.0.8.dist-info/LICENSE
whatsapp_api_webhook_server_python-0.0.8.dist-info/METADATA
whatsapp_api_webhook_server_python-0.0.8.dist-info/WHEEL
whatsapp_api_webhook_server_python-0.0.8.dist-info/top_level.txt
whatsapp_api_webhook_server_python-0.0.8.dist-info/RECORD
